client/chat.py
client/helpers/tunnel_activity.py
oldie_goldie-0.5.10.dist-info/licenses/LICENSE
server/server.py
server/helpers/tunnel_manager.py
shared/__init__.py
shared/art_forms.py
shared/command_handler.py
shared/protocol.py
shared/crypto/encryption_handlers.py
shared/crypto/session_keys.py
utilities/__init__.py
utilities/async_io.py
oldie_goldie-0.5.10.dist-info/METADATA
oldie_goldie-0.5.10.dist-info/WHEEL
oldie_goldie-0.5.10.dist-info/entry_points.txt
oldie_goldie-0.5.10.dist-info/top_level.txt
oldie_goldie-0.5.10.dist-info/RECORD
