Metadata-Version: 2.4
Name: oldie-goldie
Version: 0.5.10
Summary: Oldie Goldie — a peer-to-peer encrypted chat with tunnel and token-based access.
Home-page: https://github.com/venukotamraju/Oldie-Goldie
Author: Venu Kotamraju
Author-email: Venu kotamraju <kotamraju.venugopal@gmail.com>
Maintainer-email: Venu kotamraju <kotamraju.venugopal@gmail.com>
License:                                  Apache License
Project-URL: Homepage, https://github.com/venukotamraju/Oldie-Goldie
Project-URL: Repository, https://github.com/venukotamraju/Oldie-Goldie
Project-URL: Issues, https://github.com/venukotamraju/Oldie-Goldie/issues
Project-URL: Changelog, https://github.com/venukotamraju/Oldie-Goldie/blob/main/CHANGELOG.md
Project-URL: Documentation, https://venukotamraju.github.io/Oldie-Goldie
Keywords: chat,encryption,tunnel,websocket,secure
Classifier: Development Status :: 4 - Beta
Classifier: Programming Language :: Python :: 3.10
Classifier: Programming Language :: Python :: 3.11
Classifier: Programming Language :: Python :: 3.12
Classifier: Programming Language :: Python :: 3.13
Classifier: Topic :: Communications :: Chat
Classifier: License :: OSI Approved :: Apache Software License
Classifier: Intended Audience :: Developers
Requires-Python: <3.14,>=3.10
License-File: LICENSE
Requires-Dist: cryptography<50,>=42; sys_platform != "emscripten"
Requires-Dist: cffi<2,>=1.15; platform_machine != "wasm32"
Requires-Dist: prompt_toolkit>=3.0.51
Requires-Dist: pycparser>=2.22
Requires-Dist: wcwidth>=0.2.13
Requires-Dist: websockets<16,>=15
Provides-Extra: dev
Requires-Dist: pytest; extra == "dev"
Requires-Dist: black; extra == "dev"
Requires-Dist: build; extra == "dev"
Requires-Dist: twine; extra == "dev"
Requires-Dist: wheel; extra == "dev"
Requires-Dist: setuptools; extra == "dev"
Requires-Dist: bumpver; extra == "dev"
Provides-Extra: docs
Requires-Dist: mkdocs>=1.6.0; extra == "docs"
Requires-Dist: mkdocs-material>=9.5.20; extra == "docs"
Requires-Dist: mkdocs-awesome-pages-plugin>=2.9.2; extra == "docs"
Dynamic: license-file
